parrot1/__init__.py
parrot1/__main__.py
parrot1/audio/__init__.py
parrot1/audio/extraction/__init__.py
parrot1/audio/extraction/audio_extraction.py
parrot1/audio/transcription/__init__.py
parrot1/audio/transcription/model.py
parrot1/audio/transcription/transcribe.py
parrot1/audio/transcription/transcript/__init__.py
parrot1/audio/transcription/transcript/microsoftstream.py
parrot1/audio/transcription/transcript/transcript_type.py
parrot1/audio/utils/__init__.py
parrot1/audio/utils/plotting.py
parrot1/audio/utils/silence.py
parrot1/commons/__init__.py
parrot1/commons/asr/__init__.py
parrot1/commons/asr/base.py
parrot1/commons/asr/faster_whisper.py
parrot1/commons/asr/openai_whisper.py
parrot1/commons/asr/utils.py
parrot1/commons/generative/__init__.py
parrot1/commons/generative/base.py
parrot1/commons/generative/llamacpp.py
parrot1/commons/generative/openai_gpt.py
parrot1/commons/models/__init__.py
parrot1/commons/models/language.py
parrot1/config/__init__.py
parrot1/config/config.py
parrot1/config/config_model.py
parrot1/recap/__init__.py
parrot1/recap/recap_generator.py
parrot1/recap/tasks.py
parrot1/resources/default_configs.json
parrot1/utils/__init__.py
parrot1/utils/file_utils.py
parrot1/utils/itertools.py
parrot1-0.1.2.dist-info/LICENSE
parrot1-0.1.2.dist-info/METADATA
parrot1-0.1.2.dist-info/WHEEL
parrot1-0.1.2.dist-info/entry_points.txt
parrot1-0.1.2.dist-info/RECORD
