Metadata-Version: 2.1
Name: parrot1
Version: 0.1.2
Summary: A tool for writing a recap mail or report from a video recording of a call
Author: Gerlando Re
Author-email: gerlaxrex@gmail.com
Requires-Python: >=3.9,<=3.13
Classifier: Programming Language :: Python :: 3
Classifier: Programming Language :: Python :: 3.9
Classifier: Programming Language :: Python :: 3.10
Classifier: Programming Language :: Python :: 3.11
Classifier: Programming Language :: Python :: 3.12
Provides-Extra: all
Provides-Extra: docx
Provides-Extra: faster-whisper
Provides-Extra: llama-cpp
Provides-Extra: os-models
Provides-Extra: plotting
Requires-Dist: faster-whisper (>=0.9.0,<0.10.0) ; extra == "faster-whisper" or extra == "os-models" or extra == "all"
Requires-Dist: ffmpeg-python (>=0.2.0,<0.3.0)
Requires-Dist: huggingface-hub (>=0.19.4,<0.20.0) ; extra == "llama-cpp" or extra == "os-models" or extra == "all"
Requires-Dist: llama-cpp-python (>=0.2.20,<0.3.0) ; extra == "llama-cpp" or extra == "os-models" or extra == "all"
Requires-Dist: matplotlib (>=3.8.1,<3.9.0) ; extra == "plotting" or extra == "all"
Requires-Dist: numpy (>=1.26.2,<2.0.0)
Requires-Dist: openai (>=1.2.2,<1.3.0)
Requires-Dist: pydantic (>=2.6.1,<3.0.0)
Requires-Dist: pydub (>=0.25.1,<0.26.0)
Requires-Dist: python-docx (>=1.1.0,<1.2.0) ; extra == "docx" or extra == "all"
Requires-Dist: pytimeparse2 (>=1.7.1,<1.8.0) ; extra == "docx" or extra == "all"
Requires-Dist: typer[all] (>=0.9.0,<0.10.0)
